restest.py
lib/__init__.py
lib/cols.py
lib/engine.py
lib/expr_parser.py
lib/parser.py
lib/path_parser.py
lib/postman_exp.py
lib/timings.py
lib/utils.py
restest-2.5.0.dist-info/licenses/LICENSE
restest-2.5.0.dist-info/METADATA
restest-2.5.0.dist-info/WHEEL
restest-2.5.0.dist-info/entry_points.txt
restest-2.5.0.dist-info/top_level.txt
restest-2.5.0.dist-info/RECORD
